setup.py
groq_cli.egg-info/PKG-INFO
groq_cli.egg-info/SOURCES.txt
groq_cli.egg-info/dependency_links.txt
groq_cli.egg-info/entry_points.txt
groq_cli.egg-info/requires.txt
groq_cli.egg-info/top_level.txt
groq_cli_chat/__init__.py
groq_cli_chat/work.py