Metadata-Version: 2.1
Name: groq-cli
Version: 0.1.2
Summary: A CLI package for interacting with the Groq API.
Home-page: https://github.com/Akshad135/groq-cli
Author: Akshad Agrawal
Requires-Dist: groq
